XNBConfig/__init__.py
XNBConfig-1.0.dist-info/METADATA
XNBConfig-1.0.dist-info/WHEEL
XNBConfig-1.0.dist-info/top_level.txt
XNBConfig-1.0.dist-info/RECORD
