Metadata-Version: 2.1
Name: XNBConfig
Version: 1.0
Summary: 更简单的配置
Home-page: https://gitee.com/This-is-XiaoDeng/xnbconfig
Author: XiaoDeng3386 & FZZkill
Author-email: 1744793737@qq.com
License: UNKNOWN
Platform: UNKNOWN
Classifier: Programming Language :: Python :: 3
Classifier: License :: OSI Approved :: MIT License
Classifier: Operating System :: OS Independent
Requires-Python: >=3.8
